ansibleguy_runner/__init__.py
ansibleguy_runner/__main__.py
ansibleguy_runner/cleanup.py
ansibleguy_runner/defaults.py
ansibleguy_runner/exceptions.py
ansibleguy_runner/interface.py
ansibleguy_runner/loader.py
ansibleguy_runner/output.py
ansibleguy_runner/runner.py
ansibleguy_runner/runner_config.py
ansibleguy_runner/streaming.py
ansibleguy_runner/config/__init__.py
ansibleguy_runner/config/_base.py
ansibleguy_runner/config/ansible_cfg.py
ansibleguy_runner/config/command.py
ansibleguy_runner/config/doc.py
ansibleguy_runner/config/inventory.py
ansibleguy_runner/config/runner.py
ansibleguy_runner/display_callback/__init__.py
ansibleguy_runner/display_callback/callback/__init__.py
ansibleguy_runner/display_callback/callback/awx_display.py
ansibleguy_runner/plugins/__init__.py
ansibleguy_runner/utils/__init__.py
ansibleguy_runner/utils/base64io.py
ansibleguy_runner/utils/capacity.py
ansibleguy_runner/utils/importlib_compat.py
ansibleguy_runner/utils/streaming.py
ansibleguy_runner-2.4.0.post5.dist-info/LICENSE-2.0.txt
ansibleguy_runner-2.4.0.post5.dist-info/LICENSE.md
ansibleguy_runner-2.4.0.post5.dist-info/LICENSE.txt
ansibleguy_runner-2.4.0.post5.dist-info/METADATA
ansibleguy_runner-2.4.0.post5.dist-info/WHEEL
ansibleguy_runner-2.4.0.post5.dist-info/top_level.txt
ansibleguy_runner-2.4.0.post5.dist-info/RECORD
