Metadata-Version: 2.1
Name: ansibleguy-runner
Version: 2.4.0.post5
Summary: Ansible Runner Fork
Home-page: https://ansible-runner.readthedocs.io
Author: Ansible, Inc.
Author-email: AnsibleGuy <contact@ansibleguy.net>
License: --2024-10-05 21:14:09--  https://www.apache.org/licenses/LICENSE-2.0.txt
Project-URL: Homepage, https://github.com/ansibleguy/ansible-runner
Project-URL: Repository, https://github.com/ansibleguy/ansible-runner.git
Project-URL: Issues, https://github.com/ansibleguy/issues
Keywords: ansible,runner,automation,iac
Classifier: Programming Language :: Python :: 3
Requires-Python: >=3.9
License-File: LICENSE-2.0.txt
License-File: LICENSE.md
License-File: LICENSE.txt
Requires-Dist: pexpect >=4.5
Requires-Dist: packaging
Requires-Dist: python-daemon
Requires-Dist: pyyaml
Requires-Dist: importlib-metadata <6.3,>=4.6
